dendroptimized-0.2.2.dist-info/WHEEL
dendroptimized-0.2.2.dist-info/METADATA
dendroptimized-0.2.2.dist-info/RECORD
dendroptimized-0.2.2.dist-info/licenses/LICENSE
dendroptimized/__init__.py
dendroptimized/__about__.py
dendroptimized/dendroptimized_ext.cpython-312-x86_64-linux-gnu.so
