Metadata-Version: 2.1
Name: dendroptimized
Version: 0.2.2
Summary: Optimized C++ algorithms for dendromatics
Keywords: dendromatics,point clouds,3D,LiDAR
Author-Email: Carlos Cabo <carloscabo@uniovi.es>, Diego Laino <diegolainor@gmail.com>
License:                     GNU GENERAL PUBLIC LICENSE
Classifier: Development Status :: 3 - Alpha
Classifier: Programming Language :: Python
Classifier: Topic :: Scientific/Engineering
Project-URL: homepage, https://github.com/3DFin/dendroptimized
Project-URL: repository, https://github.com/3DFin/dendroptimized
Requires-Python: <3.14,>=3.9
Requires-Dist: numpy>=1.25
